config/tokeo.development.yaml
config/tokeo.production.yaml
config/tokeo.testing.yaml
config/tokeo.yaml
tokeo/__init__.py
tokeo/main.py
tokeo/controllers/__init__.py
tokeo/controllers/base.py
tokeo/core/__init__.py
tokeo/core/exc.py
tokeo/core/version.py
tokeo/core/logic/__init__.py
tokeo/core/logic/exc.py
tokeo/core/logic/utils.py
tokeo/core/utils/__init__.py
tokeo/core/utils/base.py
tokeo/core/utils/controllers.py
tokeo/core/utils/date.py
tokeo/core/utils/dict.py
tokeo/core/utils/json.py
tokeo/core/utils/modules.py
tokeo/core/utils/pdoc.py
tokeo/ext/__init__.py
tokeo/ext/appenv.py
tokeo/ext/appshare.py
tokeo/ext/argparse.py
tokeo/ext/automate.py
tokeo/ext/diskcache.py
tokeo/ext/dramatiq.py
tokeo/ext/grpc.py
tokeo/ext/jinja2.py
tokeo/ext/nicegui.py
tokeo/ext/pdoc.py
tokeo/ext/pocketbase.py
tokeo/ext/print.py
tokeo/ext/scheduler.py
tokeo/ext/smtp.py
tokeo/ext/yaml.py
tokeo/templates/__init__.py
tokeo/templates/generate/project/.generate.yml
tokeo/templates/generate/project/.gitignore
tokeo/templates/generate/project/CHANGELOG.md
tokeo/templates/generate/project/Dockerfile
tokeo/templates/generate/project/LICENSE.md
tokeo/templates/generate/project/MANIFEST.in
tokeo/templates/generate/project/Makefile
tokeo/templates/generate/project/README.md
tokeo/templates/generate/project/TODO.md
tokeo/templates/generate/project/pyproject.toml
tokeo/templates/generate/project/config/{{app_label}}.development.local.yaml
tokeo/templates/generate/project/config/{{app_label}}.development.yaml
tokeo/templates/generate/project/config/{{app_label}}.production.local.yaml
tokeo/templates/generate/project/config/{{app_label}}.production.yaml
tokeo/templates/generate/project/config/{{app_label}}.testing.local.yaml
tokeo/templates/generate/project/config/{{app_label}}.testing.yaml
tokeo/templates/generate/project/config/{{app_label}}.yaml
tokeo/templates/generate/project/docs/.gitkeep
tokeo/templates/generate/project/public/favicon.ico
tokeo/templates/generate/project/tests/__init__.py
tokeo-1.1.6.dist-info/licenses/LICENSE.md
tokeo-1.1.6.dist-info/METADATA
tokeo-1.1.6.dist-info/WHEEL
tokeo-1.1.6.dist-info/entry_points.txt
tokeo-1.1.6.dist-info/top_level.txt
tokeo-1.1.6.dist-info/RECORD
