Metadata-Version: 2.4
Name: tokeo
Version: 1.1.6
Summary: The Tokeo CLI contains all the dramatiq workers and publishers.
Author-email: Tom Freudenberg <th.freudenberg@gmail.com>
License-Expression: MIT
Project-URL: Homepage, https://github.com/tokeo/tokeo
Requires-Python: >=3.10
License-File: LICENSE.md
Requires-Dist: cement==3.0.12
Requires-Dist: cement[jinja2]
Requires-Dist: jinja2
Requires-Dist: cement[yaml]
Requires-Dist: PyYAML
Requires-Dist: cement[colorlog]
Requires-Dist: colorlog
Requires-Dist: pdoc3
Requires-Dist: lazy_loader
Provides-Extra: dev
Requires-Dist: pip-tools; extra == "dev"
Requires-Dist: pytest; extra == "dev"
Requires-Dist: pytest-cov; extra == "dev"
Requires-Dist: coverage; extra == "dev"
Requires-Dist: twine>=1.11.0; extra == "dev"
Requires-Dist: setuptools>=38.6.0; extra == "dev"
Requires-Dist: wheel>=0.31.0; extra == "dev"
Requires-Dist: pyink; extra == "dev"
Requires-Dist: flake8; extra == "dev"
Requires-Dist: prompt_toolkit; extra == "dev"
Requires-Dist: diskcache; extra == "dev"
Requires-Dist: dramatiq; extra == "dev"
Requires-Dist: dramatiq[rabbitmq]; extra == "dev"
Requires-Dist: pika; extra == "dev"
Requires-Dist: grpcio; extra == "dev"
Requires-Dist: grpcio-tools; extra == "dev"
Requires-Dist: protobuf; extra == "dev"
Requires-Dist: apscheduler<4.0,>=3.0; extra == "dev"
Requires-Dist: requests; extra == "dev"
Requires-Dist: nicegui; extra == "dev"
Requires-Dist: fastapi; extra == "dev"
Requires-Dist: starlette; extra == "dev"
Requires-Dist: pscript; extra == "dev"
Requires-Dist: vbuild; extra == "dev"
Requires-Dist: pocketbase; extra == "dev"
Requires-Dist: invoke; extra == "dev"
Requires-Dist: fabric; extra == "dev"
Requires-Dist: paramiko; extra == "dev"
Dynamic: license-file
